<?xml version='1.0' encoding='UTF-8'?><magicdraw><package id="_19_0_3_68e0225_1642672857507_756619_19" refElementId="_19_0_3_68e0225_1642672857507_756619_19" humanType="Package" classType="Package" requireSort="node" icon="WebReport2_files/icon_package_315785478.svg"><documentation humanName="Documentation" mode="s">The {{term(Device Information Model)}} provides a representation of the physical and logical configuration for a piece of equipment used for a manufacturing process or for any other purpose.  It also provides the definition of data that may be reported by that equipment. 

Using information defined in the {{term(Device Information Model)}}, a software application can determine the configuration and reporting capabilities of a piece of equipment.  To do this, the software application issues a {{term(probe request)}} (defined in {{package(Fundamentals)}}) to an {{term(agent)}} associated with a piece of equipment. An {{term(agent)}} responds to the {{term(probe request)}} with an {{term(MTConnectDevices Response Document)}} that contains information describing both the physical and logical structure of the piece of equipment and a detailed description of each {{term(Observation)}} that can be reported by the {{term(agent)}} associated with the piece of equipment. This information allows the client software application to interpret the document and to extract the data with the same meaning, value, and context that it had at its original source.  

The {{term(MTConnectDevices Response Document)}} is comprised of two sections: {{block(Header)}} and {{block(Devices)}}.

The {{block(Header)}} section contains protocol related information as defined in {{package(Fundamentals)}}.

The {{block(Devices)}} section of the {{term(MTConnectDevices Response Document)}} contains a {{block(Device)}} entity for each piece of equipment described in the document.  Each {{block(Device)}} is comprised of two primary types of entities - {{termplural(Component)}} and {{termplural(DataItem)}}.  

{{termplural(Component)}} organize information that represents the physical and logical parts and sub-parts of a piece of equipment (See {{package(Components)}} for more details).  

{{termplural(DataItem)}} describe data that can be reported by a piece of equipment.  In the {{term(Device Information Model)}}, {{termplural(DataItem)}} are defined as {{block(DataItem)}} entities (See {{package(DataItem Types)}}).

The {{termplural(Component)}} and {{termplural(DataItem)}} in the {{term(MTConnectDevices Response Document)}} provide information representing the physical and logical structure for a piece of equipment and the types of data that the piece of equipment can report relative to that structure.   The {{term(MTConnectDevices Response Document)}} does not contain values for the data types reported by the piece of equipment.  The {{term(MTConnectStreams Response Document)}} defined in {{package(Observation Information Model)}} provides the data values that are reported by the piece of equipment.

> Note:  The MTConnect Standard also defines the information model for {{termplural(asset)}}.  An {{term(asset)}} is something that is used in the manufacturing process, but is not permanently associated with a single piece of equipment, can be removed from the piece of equipment without compromising its function, and can be associated with other pieces of equipment during its lifecycle.  See {{package(Asset Information Model)}} for more details on {{termplural(asset)}}.
</documentation><visibility humanName="Visibility">public</visibility><taggedValue humanName="Tagged Value"><stringtaggedvalue refid="_19_0_3_68e0225_1642673792778_333934_78application_19_0_1_936029d_1515407574391_680709_4531" refElementId="_19_0_3_68e0225_1642673792778_333934_78application_19_0_1_936029d_1515407574391_680709_4531" humanType="String Tagged Value" classType="StringTaggedValue" name="sortPriority = &quot;11&quot;" icon="WebReport2_files/icon_stringtaggedvalue_1751196638.svg"/></taggedValue><qualifiedName humanName="Qualified Name" mode="e">Device Information Model</qualifiedName><packagedElement humanName="Packaged Element"><package refid="EAPK_6F87CB48_AFED_473f_92DF_E7AFDAFD3CAC" refElementId="EAPK_6F87CB48_AFED_473f_92DF_E7AFDAFD3CAC" humanType="Package" classType="Package" name="Components" icon="WebReport2_files/icon_package_315785478.svg"/><package refid="EAPK_3D92D585_AB2B_4fe0_8B49_2F22359705CA" refElementId="EAPK_3D92D585_AB2B_4fe0_8B49_2F22359705CA" humanType="Package" classType="Package" name="Compositions" hasDiagram="true" icon="WebReport2_files/icon_package_315785478.svg"/><package refid="EAPK_0FAC31E7_7957_49d2_AD4C_BCFBEF9878FD" refElementId="EAPK_0FAC31E7_7957_49d2_AD4C_BCFBEF9878FD" humanType="Package" classType="Package" name="DataItems" hasDiagram="true" icon="WebReport2_files/icon_package_315785478.svg"/><package refid="EAPK_F54CCA63_E73C_468b_B64E_F97DEE70FFC6" refElementId="EAPK_F54CCA63_E73C_468b_B64E_F97DEE70FFC6" humanType="Package" classType="Package" name="References" hasDiagram="true" icon="WebReport2_files/icon_package_315785478.svg"/><package refid="_19_0_3_91b028d_1579526876433_244855_7626" refElementId="_19_0_3_91b028d_1579526876433_244855_7626" humanType="Package" classType="Package" name="Configurations" hasDiagram="true" icon="WebReport2_files/icon_package_315785478.svg"/><block refid="_19_0_3_68e0225_1620240839406_285612_1596" refElementId="_19_0_3_68e0225_1620240839406_285612_1596" humanType="Block" classType="Class" name="Device" icon="WebReport2_files/icon_block_2124604867.svg"/><association refid="_19_0_3_68e0225_1651666688556_861230_268" refElementId="_19_0_3_68e0225_1651666688556_861230_268" humanType="Association" classType="Association" name="Association[Device Information Model::Device -> observesAvailability:Observation Information Model::Observation Types::Event Types::Availability]" isRelationship="true" icon="WebReport2_files/icon_association_1770950012.svg"/><association refid="_19_0_3_68e0225_1651666715648_36999_289" refElementId="_19_0_3_68e0225_1651666715648_36999_289" humanType="Association" classType="Association" name="Association[Device Information Model::Device -> observesAssetChanged:Observation Information Model::Observation Types::Event Types::AssetChanged]" isRelationship="true" icon="WebReport2_files/icon_association_1770950012.svg"/><association refid="_19_0_3_68e0225_1651666729427_936813_310" refElementId="_19_0_3_68e0225_1651666729427_936813_310" humanType="Association" classType="Association" name="Association[Device Information Model::Device -> observesAssetRemoved:Observation Information Model::Observation Types::Event Types::AssetRemoved]" isRelationship="true" icon="WebReport2_files/icon_association_1770950012.svg"/></packagedElement><owningPackage refid="_19_0_3_45f01b9_1577483680855_804517_0" refElementId="_19_0_3_45f01b9_1577483680855_804517_0" humanType="Model" classType="Model" name="MTConnect" icon="WebReport2_files/icon_model_1961696565.svg" humanName="Owning Package"/><owner refid="_19_0_3_45f01b9_1577483680855_804517_0" refElementId="_19_0_3_45f01b9_1577483680855_804517_0" humanType="Model" classType="Model" name="MTConnect" icon="WebReport2_files/icon_model_1961696565.svg" humanName="Owner" mode="s,e"/><ownedType humanName="Owned Type"><block refid="_19_0_3_68e0225_1620240839406_285612_1596" refElementId="_19_0_3_68e0225_1620240839406_285612_1596" humanType="Block" classType="Class" name="Device" icon="WebReport2_files/icon_block_2124604867.svg"/><association refid="_19_0_3_68e0225_1651666688556_861230_268" refElementId="_19_0_3_68e0225_1651666688556_861230_268" humanType="Association" classType="Association" name="Association[Device Information Model::Device -> observesAvailability:Observation Information Model::Observation Types::Event Types::Availability]" isRelationship="true" icon="WebReport2_files/icon_association_1770950012.svg"/><association refid="_19_0_3_68e0225_1651666715648_36999_289" refElementId="_19_0_3_68e0225_1651666715648_36999_289" humanType="Association" classType="Association" name="Association[Device Information Model::Device -> observesAssetChanged:Observation Information Model::Observation Types::Event Types::AssetChanged]" isRelationship="true" icon="WebReport2_files/icon_association_1770950012.svg"/><association refid="_19_0_3_68e0225_1651666729427_936813_310" refElementId="_19_0_3_68e0225_1651666729427_936813_310" humanType="Association" classType="Association" name="Association[Device Information Model::Device -> observesAssetRemoved:Observation Information Model::Observation Types::Event Types::AssetRemoved]" isRelationship="true" icon="WebReport2_files/icon_association_1770950012.svg"/></ownedType><ownedMember humanName="Owned Member"><package refid="EAPK_6F87CB48_AFED_473f_92DF_E7AFDAFD3CAC" refElementId="EAPK_6F87CB48_AFED_473f_92DF_E7AFDAFD3CAC" humanType="Package" classType="Package" name="Components" icon="WebReport2_files/icon_package_315785478.svg"/><package refid="EAPK_3D92D585_AB2B_4fe0_8B49_2F22359705CA" refElementId="EAPK_3D92D585_AB2B_4fe0_8B49_2F22359705CA" humanType="Package" classType="Package" name="Compositions" hasDiagram="true" icon="WebReport2_files/icon_package_315785478.svg"/><package refid="EAPK_0FAC31E7_7957_49d2_AD4C_BCFBEF9878FD" refElementId="EAPK_0FAC31E7_7957_49d2_AD4C_BCFBEF9878FD" humanType="Package" classType="Package" name="DataItems" hasDiagram="true" icon="WebReport2_files/icon_package_315785478.svg"/><package refid="EAPK_F54CCA63_E73C_468b_B64E_F97DEE70FFC6" refElementId="EAPK_F54CCA63_E73C_468b_B64E_F97DEE70FFC6" humanType="Package" classType="Package" name="References" hasDiagram="true" icon="WebReport2_files/icon_package_315785478.svg"/><package refid="_19_0_3_91b028d_1579526876433_244855_7626" refElementId="_19_0_3_91b028d_1579526876433_244855_7626" humanType="Package" classType="Package" name="Configurations" hasDiagram="true" icon="WebReport2_files/icon_package_315785478.svg"/><block refid="_19_0_3_68e0225_1620240839406_285612_1596" refElementId="_19_0_3_68e0225_1620240839406_285612_1596" humanType="Block" classType="Class" name="Device" icon="WebReport2_files/icon_block_2124604867.svg"/><association refid="_19_0_3_68e0225_1651666688556_861230_268" refElementId="_19_0_3_68e0225_1651666688556_861230_268" humanType="Association" classType="Association" name="Association[Device Information Model::Device -> observesAvailability:Observation Information Model::Observation Types::Event Types::Availability]" isRelationship="true" icon="WebReport2_files/icon_association_1770950012.svg"/><association refid="_19_0_3_68e0225_1651666715648_36999_289" refElementId="_19_0_3_68e0225_1651666715648_36999_289" humanType="Association" classType="Association" name="Association[Device Information Model::Device -> observesAssetChanged:Observation Information Model::Observation Types::Event Types::AssetChanged]" isRelationship="true" icon="WebReport2_files/icon_association_1770950012.svg"/><association refid="_19_0_3_68e0225_1651666729427_936813_310" refElementId="_19_0_3_68e0225_1651666729427_936813_310" humanType="Association" classType="Association" name="Association[Device Information Model::Device -> observesAssetRemoved:Observation Information Model::Observation Types::Event Types::AssetRemoved]" isRelationship="true" icon="WebReport2_files/icon_association_1770950012.svg"/><diagram refid="_19_0_3_91b028d_1579271366865_490147_505" refElementId="_19_0_3_91b028d_1579271366865_490147_505" humanType="Diagram" classType="Diagram" name="Components" diagramType="SysML Block Definition Diagram" icon="WebReport2_files/icon_SysML Block Definition Diagram_718153409.svg"/><diagram refid="_19_0_3_68e0225_1648550155707_800299_22" refElementId="_19_0_3_68e0225_1648550155707_800299_22" humanType="Diagram" classType="Diagram" name="Components for Device" diagramType="SysML Block Definition Diagram" icon="WebReport2_files/icon_SysML Block Definition Diagram_718153409.svg"/></ownedMember><ownedElement humanName="Owned Element"><stringtaggedvalue refid="_19_0_3_68e0225_1642673792778_333934_78application_19_0_1_936029d_1515407574391_680709_4531" refElementId="_19_0_3_68e0225_1642673792778_333934_78application_19_0_1_936029d_1515407574391_680709_4531" humanType="String Tagged Value" classType="StringTaggedValue" name="sortPriority = &quot;11&quot;" icon="WebReport2_files/icon_stringtaggedvalue_1751196638.svg"/><package refid="EAPK_6F87CB48_AFED_473f_92DF_E7AFDAFD3CAC" refElementId="EAPK_6F87CB48_AFED_473f_92DF_E7AFDAFD3CAC" humanType="Package" classType="Package" name="Components" icon="WebReport2_files/icon_package_315785478.svg"/><package refid="EAPK_3D92D585_AB2B_4fe0_8B49_2F22359705CA" refElementId="EAPK_3D92D585_AB2B_4fe0_8B49_2F22359705CA" humanType="Package" classType="Package" name="Compositions" hasDiagram="true" icon="WebReport2_files/icon_package_315785478.svg"/><package refid="EAPK_0FAC31E7_7957_49d2_AD4C_BCFBEF9878FD" refElementId="EAPK_0FAC31E7_7957_49d2_AD4C_BCFBEF9878FD" humanType="Package" classType="Package" name="DataItems" hasDiagram="true" icon="WebReport2_files/icon_package_315785478.svg"/><package refid="EAPK_F54CCA63_E73C_468b_B64E_F97DEE70FFC6" refElementId="EAPK_F54CCA63_E73C_468b_B64E_F97DEE70FFC6" humanType="Package" classType="Package" name="References" hasDiagram="true" icon="WebReport2_files/icon_package_315785478.svg"/><package refid="_19_0_3_91b028d_1579526876433_244855_7626" refElementId="_19_0_3_91b028d_1579526876433_244855_7626" humanType="Package" classType="Package" name="Configurations" hasDiagram="true" icon="WebReport2_files/icon_package_315785478.svg"/><block refid="_19_0_3_68e0225_1620240839406_285612_1596" refElementId="_19_0_3_68e0225_1620240839406_285612_1596" humanType="Block" classType="Class" name="Device" icon="WebReport2_files/icon_block_2124604867.svg"/><association refid="_19_0_3_68e0225_1651666688556_861230_268" refElementId="_19_0_3_68e0225_1651666688556_861230_268" humanType="Association" classType="Association" name="Association[Device Information Model::Device -> observesAvailability:Observation Information Model::Observation Types::Event Types::Availability]" isRelationship="true" icon="WebReport2_files/icon_association_1770950012.svg"/><association refid="_19_0_3_68e0225_1651666715648_36999_289" refElementId="_19_0_3_68e0225_1651666715648_36999_289" humanType="Association" classType="Association" name="Association[Device Information Model::Device -> observesAssetChanged:Observation Information Model::Observation Types::Event Types::AssetChanged]" isRelationship="true" icon="WebReport2_files/icon_association_1770950012.svg"/><association refid="_19_0_3_68e0225_1651666729427_936813_310" refElementId="_19_0_3_68e0225_1651666729427_936813_310" humanType="Association" classType="Association" name="Association[Device Information Model::Device -> observesAssetRemoved:Observation Information Model::Observation Types::Event Types::AssetRemoved]" isRelationship="true" icon="WebReport2_files/icon_association_1770950012.svg"/><diagram refid="_19_0_3_91b028d_1579271366865_490147_505" refElementId="_19_0_3_91b028d_1579271366865_490147_505" humanType="Diagram" classType="Diagram" name="Components" diagramType="SysML Block Definition Diagram" icon="WebReport2_files/icon_SysML Block Definition Diagram_718153409.svg"/><diagram refid="_19_0_3_68e0225_1648550155707_800299_22" refElementId="_19_0_3_68e0225_1648550155707_800299_22" humanType="Diagram" classType="Diagram" name="Components for Device" diagramType="SysML Block Definition Diagram" icon="WebReport2_files/icon_SysML Block Definition Diagram_718153409.svg"/><comment refid="_19_0_3_68e0225_1642674191850_803048_106" refElementId="_19_0_3_68e0225_1642674191850_803048_106" humanType="Comment" classType="Comment" name="The {{term(Device Information Model)}} provides a ..." icon="WebReport2_files/icon_comment_895580618.svg"/><comment refid="_19_0_3_68e0225_1678885645020_485463_2678" refElementId="_19_0_3_68e0225_1678885645020_485463_2678" humanType="Comment" classType="Comment" name="Devices Appendix" icon="WebReport2_files/icon_comment_1090073068.svg"/></ownedElement><ownedDiagram humanName="Owned Diagram"><diagram refid="_19_0_3_91b028d_1579271366865_490147_505" refElementId="_19_0_3_91b028d_1579271366865_490147_505" humanType="Diagram" classType="Diagram" name="Components" diagramType="SysML Block Definition Diagram" icon="WebReport2_files/icon_SysML Block Definition Diagram_718153409.svg"/><diagram refid="_19_0_3_68e0225_1648550155707_800299_22" refElementId="_19_0_3_68e0225_1648550155707_800299_22" humanType="Diagram" classType="Diagram" name="Components for Device" diagramType="SysML Block Definition Diagram" icon="WebReport2_files/icon_SysML Block Definition Diagram_718153409.svg"/></ownedDiagram><ownedComment humanName="Owned Comment"><comment refid="_19_0_3_68e0225_1642674191850_803048_106" refElementId="_19_0_3_68e0225_1642674191850_803048_106" humanType="Comment" classType="Comment" name="The {{term(Device Information Model)}} provides a ..." icon="WebReport2_files/icon_comment_895580618.svg"/><comment refid="_19_0_3_68e0225_1678885645020_485463_2678" refElementId="_19_0_3_68e0225_1678885645020_485463_2678" humanType="Comment" classType="Comment" name="Devices Appendix" icon="WebReport2_files/icon_comment_1090073068.svg"/></ownedComment><nestingPackage refid="_19_0_3_45f01b9_1577483680855_804517_0" refElementId="_19_0_3_45f01b9_1577483680855_804517_0" humanType="Model" classType="Model" name="MTConnect" icon="WebReport2_files/icon_model_1961696565.svg" humanName="Nesting Package"/><nestedPackage humanName="Nested Package"><package refid="EAPK_6F87CB48_AFED_473f_92DF_E7AFDAFD3CAC" refElementId="EAPK_6F87CB48_AFED_473f_92DF_E7AFDAFD3CAC" humanType="Package" classType="Package" name="Components" icon="WebReport2_files/icon_package_315785478.svg"/><package refid="EAPK_3D92D585_AB2B_4fe0_8B49_2F22359705CA" refElementId="EAPK_3D92D585_AB2B_4fe0_8B49_2F22359705CA" humanType="Package" classType="Package" name="Compositions" hasDiagram="true" icon="WebReport2_files/icon_package_315785478.svg"/><package refid="EAPK_0FAC31E7_7957_49d2_AD4C_BCFBEF9878FD" refElementId="EAPK_0FAC31E7_7957_49d2_AD4C_BCFBEF9878FD" humanType="Package" classType="Package" name="DataItems" hasDiagram="true" icon="WebReport2_files/icon_package_315785478.svg"/><package refid="EAPK_F54CCA63_E73C_468b_B64E_F97DEE70FFC6" refElementId="EAPK_F54CCA63_E73C_468b_B64E_F97DEE70FFC6" humanType="Package" classType="Package" name="References" hasDiagram="true" icon="WebReport2_files/icon_package_315785478.svg"/><package refid="_19_0_3_91b028d_1579526876433_244855_7626" refElementId="_19_0_3_91b028d_1579526876433_244855_7626" humanType="Package" classType="Package" name="Configurations" hasDiagram="true" icon="WebReport2_files/icon_package_315785478.svg"/></nestedPackage><namespace refid="_19_0_3_45f01b9_1577483680855_804517_0" refElementId="_19_0_3_45f01b9_1577483680855_804517_0" humanType="Model" classType="Model" name="MTConnect" icon="WebReport2_files/icon_model_1961696565.svg" humanName="Namespace"/><name humanName="Name" mode="s,e">Device Information Model</name><member humanName="Member"><package refid="EAPK_6F87CB48_AFED_473f_92DF_E7AFDAFD3CAC" refElementId="EAPK_6F87CB48_AFED_473f_92DF_E7AFDAFD3CAC" humanType="Package" classType="Package" name="Components" icon="WebReport2_files/icon_package_315785478.svg"/><package refid="EAPK_3D92D585_AB2B_4fe0_8B49_2F22359705CA" refElementId="EAPK_3D92D585_AB2B_4fe0_8B49_2F22359705CA" humanType="Package" classType="Package" name="Compositions" hasDiagram="true" icon="WebReport2_files/icon_package_315785478.svg"/><package refid="EAPK_0FAC31E7_7957_49d2_AD4C_BCFBEF9878FD" refElementId="EAPK_0FAC31E7_7957_49d2_AD4C_BCFBEF9878FD" humanType="Package" classType="Package" name="DataItems" hasDiagram="true" icon="WebReport2_files/icon_package_315785478.svg"/><package refid="EAPK_F54CCA63_E73C_468b_B64E_F97DEE70FFC6" refElementId="EAPK_F54CCA63_E73C_468b_B64E_F97DEE70FFC6" humanType="Package" classType="Package" name="References" hasDiagram="true" icon="WebReport2_files/icon_package_315785478.svg"/><package refid="_19_0_3_91b028d_1579526876433_244855_7626" refElementId="_19_0_3_91b028d_1579526876433_244855_7626" humanType="Package" classType="Package" name="Configurations" hasDiagram="true" icon="WebReport2_files/icon_package_315785478.svg"/><block refid="_19_0_3_68e0225_1620240839406_285612_1596" refElementId="_19_0_3_68e0225_1620240839406_285612_1596" humanType="Block" classType="Class" name="Device" icon="WebReport2_files/icon_block_2124604867.svg"/><association refid="_19_0_3_68e0225_1651666688556_861230_268" refElementId="_19_0_3_68e0225_1651666688556_861230_268" humanType="Association" classType="Association" name="Association[Device Information Model::Device -> observesAvailability:Observation Information Model::Observation Types::Event Types::Availability]" isRelationship="true" icon="WebReport2_files/icon_association_1770950012.svg"/><association refid="_19_0_3_68e0225_1651666715648_36999_289" refElementId="_19_0_3_68e0225_1651666715648_36999_289" humanType="Association" classType="Association" name="Association[Device Information Model::Device -> observesAssetChanged:Observation Information Model::Observation Types::Event Types::AssetChanged]" isRelationship="true" icon="WebReport2_files/icon_association_1770950012.svg"/><association refid="_19_0_3_68e0225_1651666729427_936813_310" refElementId="_19_0_3_68e0225_1651666729427_936813_310" humanType="Association" classType="Association" name="Association[Device Information Model::Device -> observesAssetRemoved:Observation Information Model::Observation Types::Event Types::AssetRemoved]" isRelationship="true" icon="WebReport2_files/icon_association_1770950012.svg"/><diagram refid="_19_0_3_91b028d_1579271366865_490147_505" refElementId="_19_0_3_91b028d_1579271366865_490147_505" humanType="Diagram" classType="Diagram" name="Components" diagramType="SysML Block Definition Diagram" icon="WebReport2_files/icon_SysML Block Definition Diagram_718153409.svg"/><diagram refid="_19_0_3_68e0225_1648550155707_800299_22" refElementId="_19_0_3_68e0225_1648550155707_800299_22" humanType="Diagram" classType="Diagram" name="Components for Device" diagramType="SysML Block Definition Diagram" icon="WebReport2_files/icon_SysML Block Definition Diagram_718153409.svg"/></member><appliedStereotype humanName="Applied Stereotype" mode="s,e"><stereotype refid="_19_0_1_936029d_1515407574371_700886_4529" refElementId="_19_0_1_936029d_1515407574371_700886_4529" humanType="Stereotype" classType="Stereotype" name="CustomSort" icon="WebReport2_files/icon_stereotype_1363963040.svg"/></appliedStereotype><URI humanName="URI" mode="s,e"></URI><TO_DO humanName="To Do" mode="s,e"></TO_DO><ActiveHyperlink humanName="Active Hyperlink" mode="e"></ActiveHyperlink><report_appliedStereotype_tags humanName="Applied Stereotype" requireSort="element" mode="s,e"><stereotype refid="_19_0_1_936029d_1515407574371_700886_4529" refElementId="_19_0_1_936029d_1515407574371_700886_4529" humanType="Stereotype" classType="Stereotype" name="CustomSort" icon="WebReport2_files/icon_stereotype_1363963040.svg"><property requireSort="name" refid="_19_0_1_936029d_1515407574388_944278_4530" refElementId="_19_0_1_936029d_1515407574388_944278_4530" humanType="Property" classType="Property" name="base_Element" icon="WebReport2_files/icon_property_415032321.svg" humanName="Base_ Element"/><property requireSort="name" refid="_10_0EAPbeta_be00301_1123081772098_411862_275" refElementId="_10_0EAPbeta_be00301_1123081772098_411862_275" humanType="Property" classType="Property" name="base_Element" icon="WebReport2_files/icon_property_415032321.svg" humanName="Base_ Element"/><property requireSort="name" refid="_19_0_1_936029d_1515407574391_680709_4531" refElementId="_19_0_1_936029d_1515407574391_680709_4531" humanType="Property" classType="Property" name="sortPriority" icon="WebReport2_files/icon_property_415032321.svg" humanName="Sort Priority"><String>11</String></property></stereotype></report_appliedStereotype_tags></package></magicdraw>